relace_mcp/__init__.py
relace_mcp/__main__.py
relace_mcp/server.py
relace_mcp/utils.py
relace_mcp/backend/__init__.py
relace_mcp/backend/openai_backend.py
relace_mcp/clients/__init__.py
relace_mcp/clients/apply.py
relace_mcp/clients/exceptions.py
relace_mcp/clients/repo.py
relace_mcp/clients/search.py
relace_mcp/config/__init__.py
relace_mcp/config/base_dir.py
relace_mcp/config/compat.py
relace_mcp/config/provider.py
relace_mcp/config/settings.py
relace_mcp/config/llm_prompts/apply_openai.yaml
relace_mcp/config/llm_prompts/search_openai.yaml
relace_mcp/config/llm_prompts/search_relace.yaml
relace_mcp/dashboard/__init__.py
relace_mcp/dashboard/app.py
relace_mcp/dashboard/log_reader.py
relace_mcp/dashboard/styles.tcss
relace_mcp/dashboard/widgets.py
relace_mcp/lsp/__init__.py
relace_mcp/lsp/client.py
relace_mcp/lsp/protocol.py
relace_mcp/lsp/types.py
relace_mcp/lsp/languages/__init__.py
relace_mcp/lsp/languages/base.py
relace_mcp/lsp/languages/python.py
relace_mcp/middleware/__init__.py
relace_mcp/middleware/roots.py
relace_mcp/tools/__init__.py
relace_mcp/tools/apply/__init__.py
relace_mcp/tools/apply/core.py
relace_mcp/tools/apply/encoding.py
relace_mcp/tools/apply/errors.py
relace_mcp/tools/apply/exceptions.py
relace_mcp/tools/apply/file_io.py
relace_mcp/tools/apply/logging.py
relace_mcp/tools/apply/snippet.py
relace_mcp/tools/repo/__init__.py
relace_mcp/tools/repo/clear.py
relace_mcp/tools/repo/info.py
relace_mcp/tools/repo/list.py
relace_mcp/tools/repo/search.py
relace_mcp/tools/repo/state.py
relace_mcp/tools/repo/sync.py
relace_mcp/tools/search/__init__.py
relace_mcp/tools/search/logging.py
relace_mcp/tools/search/handlers/__init__.py
relace_mcp/tools/search/handlers/bash.py
relace_mcp/tools/search/handlers/bash_security.py
relace_mcp/tools/search/handlers/constants.py
relace_mcp/tools/search/handlers/context.py
relace_mcp/tools/search/handlers/glob.py
relace_mcp/tools/search/handlers/grep_search.py
relace_mcp/tools/search/handlers/lsp.py
relace_mcp-0.2.3.dist-info/licenses/LICENSE
relace_mcp-0.2.3.dist-info/METADATA
relace_mcp-0.2.3.dist-info/WHEEL
relace_mcp-0.2.3.dist-info/entry_points.txt
relace_mcp-0.2.3.dist-info/top_level.txt
relace_mcp-0.2.3.dist-info/RECORD
