Metadata-Version: 2.4
Name: relace-mcp
Version: 0.2.3
Summary: Unofficial Relace MCP Server - Fast code merging via Relace API
Author: possible055
License: MIT
Project-URL: Repository, https://github.com/possible055/relace-mcp
Project-URL: Documentation, https://github.com/possible055/relace-mcp#readme
Project-URL: Issues, https://github.com/possible055/relace-mcp/issues
Keywords: relace,instant-apply,model-context-protocol,mcp-server
Classifier: Development Status :: 4 - Beta
Classifier: Intended Audience :: Developers
Classifier: License :: OSI Approved :: MIT License
Classifier: Programming Language :: Python :: 3
Classifier: Programming Language :: Python :: 3.11
Classifier: Programming Language :: Python :: 3.12
Classifier: Programming Language :: Python :: 3.13
Classifier: Topic :: Software Development :: Libraries :: Python Modules
Classifier: Framework :: FastAPI
Classifier: Environment :: Plugins
Requires-Python: >=3.11
License-File: LICENSE
Requires-Dist: basedpyright>=1.20.0
Requires-Dist: charset-normalizer>=3.0.0
Requires-Dist: fastmcp>=2.0.0
Requires-Dist: httpx>=0.28.0
Requires-Dist: openai>=1.0.0
Requires-Dist: platformdirs>=4.0.0
Requires-Dist: psutil>=5.9.0
Requires-Dist: python-dotenv>=1.0.0
Requires-Dist: PyYAML>=6.0.0
Requires-Dist: tenacity>=8.0.0
Provides-Extra: dev
Requires-Dist: pytest>=8.4.1; extra == "dev"
Requires-Dist: pytest-asyncio>=1.3.0; extra == "dev"
Requires-Dist: pre-commit>=4.5.1; extra == "dev"
Requires-Dist: mypy>=1.19.1; extra == "dev"
Requires-Dist: interrogate>=1.7.0; extra == "dev"
Requires-Dist: dead>=1.5.2; extra == "dev"
Requires-Dist: ruff>=0.1.0; extra == "dev"
Requires-Dist: build>=1.0.0; extra == "dev"
Requires-Dist: types-PyYAML>=6.0.0; extra == "dev"
Requires-Dist: bandit[toml]>=1.9.0; extra == "dev"
Provides-Extra: tools
Requires-Dist: textual>=0.50.0; extra == "tools"
Provides-Extra: benchmark
Requires-Dist: click>=8.0.0; extra == "benchmark"
Dynamic: license-file
